ElasticSearchHandler/__init__.py
ElasticSearchHandler-0.0.1.dist-info/LICENSE
ElasticSearchHandler-0.0.1.dist-info/METADATA
ElasticSearchHandler-0.0.1.dist-info/WHEEL
ElasticSearchHandler-0.0.1.dist-info/top_level.txt
ElasticSearchHandler-0.0.1.dist-info/RECORD
