Metadata-Version: 2.1
Name: ElasticSearchHandler
Version: 0.0.1
Summary: Elasticsearch handler for logging
Home-page: https://github.com/oleglpts/ElasticSearchHandler
Author: Oleg Lupats
Author-email: oleglupats@gmail.com
License: MIT
Platform: any
Classifier: Programming Language :: Python :: 3
License-File: LICENSE
Requires-Dist: elasticsearch7
